{"tickets":[{"userId":"100069254151118","ticketNumber":1},{"userId":"100069254151118","ticketNumber":2},{"userId":"100069254151118","ticketNumber":3},{"userId":"61573866391878","ticketNumber":4},{"userId":"61573866391878","ticketNumber":5},{"userId":"61573866391878","ticketNumber":6},{"userId":"61556251307831","ticketNumber":7},{"userId":"61556251307831","ticketNumber":8},{"userId":"61556251307831","ticketNumber":9},{"userId":"100091287365781","ticketNumber":10},{"userId":"100091287365781","ticketNumber":11},{"userId":"100091287365781","ticketNumber":12}]}
